xirvik/__init__.py
xirvik/__main__.py
xirvik/client.py
xirvik/commands/__init__.py
xirvik/commands/delete_old.py
xirvik/commands/install_services.py
xirvik/commands/move_by_label.py
xirvik/commands/move_erroneous.py
xirvik/commands/root.py
xirvik/commands/simple.py
xirvik/commands/utils.py
xirvik/py.typed
xirvik/typing.py
xirvik/utils.py
xirvik_tools-0.5.3.dist-info/METADATA
xirvik_tools-0.5.3.dist-info/WHEEL
xirvik_tools-0.5.3.dist-info/entry_points.txt
xirvik_tools-0.5.3.dist-info/licenses/LICENSE.txt
xirvik_tools-0.5.3.dist-info/RECORD
