Metadata-Version: 2.4
Name: xirvik-tools
Version: 0.5.3
Summary: Command line utilities for interfacing with Xirvik.
License-Expression: MIT
License-File: LICENSE.txt
Keywords: command line,xirvik
Author: Andrew Udvare
Author-email: audvare@gmail.com
Requires-Python: >=3.10,<4.0
Classifier: Development Status :: 4 - Beta
Classifier: Intended Audience :: Developers
Classifier: Programming Language :: Python
Classifier: Programming Language :: Python :: 3.10
Classifier: Programming Language :: Python :: 3.11
Classifier: Programming Language :: Python :: 3.12
Classifier: Programming Language :: Python :: 3.13
Classifier: Programming Language :: Python :: 3.14
Classifier: Typing :: Typed
Requires-Dist: bascom (>=0.1.0,<0.2.0)
Requires-Dist: beautifulsoup4 (>=4.14.3,<5.0.0)
Requires-Dist: cached-property (>=2.0.1,<3.0.0)
Requires-Dist: click (>=8.3.1,<9.0.0)
Requires-Dist: fabric (>=3.2.2,<4.0.0)
Requires-Dist: html5lib (>=1.1,<2.0)
Requires-Dist: keyring (>=25.7.0,<26.0.0)
Requires-Dist: mutagen (>=1.47.0,<2.0.0)
Requires-Dist: platformdirs (>=4.5.1,<5.0.0)
Requires-Dist: pyyaml (>=6.0.3,<7.0.0)
Requires-Dist: ratelimit (>=2.2.1,<3.0.0)
Requires-Dist: requests (>=2.32.5,<3.0.0)
Requires-Dist: tabulate (>=0.9.0,<0.10.0)
Requires-Dist: typing-extensions (>=4.15.0,<5.0.0)
Requires-Dist: unidecode (>=1.4.0,<2.0.0)
Project-URL: Documentation, https://xirvik-tools.readthedocs.org
Project-URL: Homepage, https://tatsh.github.io/xirvik-tools/
Project-URL: Issues, https://github.com/Tatsh/xirvik-tools/issues
Project-URL: Repository, https://github.com/Tatsh/xirvik-tools
